Metadata-Version: 2.1
Name: hello-world-vtzhd
Version: 0.0.2
Summary: Hello World package
Home-page: https://github.com/vitzhdanov/test_lib.git
Author: vtzhd
Author-email: i@zhdanov-1.ru
License: UNKNOWN
Platform: UNKNOWN
Classifier: Programming Language :: Python :: 3.8
Classifier: License :: OSI Approved :: MIT License
Classifier: Operating System :: OS Independent
Requires-Python: >=3.6
